awslabs/__init__.py
awslabs/core_mcp_server/__init__.py
awslabs/core_mcp_server/server.py
awslabs/core_mcp_server/static/PROMPT_UNDERSTANDING.md
awslabs/core_mcp_server/static/__init__.py
awslabs_core_mcp_server-1.0.21.dist-info/METADATA
awslabs_core_mcp_server-1.0.21.dist-info/WHEEL
awslabs_core_mcp_server-1.0.21.dist-info/entry_points.txt
awslabs_core_mcp_server-1.0.21.dist-info/licenses/LICENSE
awslabs_core_mcp_server-1.0.21.dist-info/licenses/NOTICE
awslabs_core_mcp_server-1.0.21.dist-info/RECORD
